MANIFEST.in
requirements.txt
setup.py
streampie.py
streampie.egg-info/PKG-INFO
streampie.egg-info/SOURCES.txt
streampie.egg-info/dependency_links.txt
streampie.egg-info/requires.txt
streampie.egg-info/top_level.txt