Metadata-Version: 1.1
Name: streampie
Version: 0.2.4
Summary: A simple, parallel stream processing library
Home-page: https://github.com/malisal/streampie
Author: Luka Malisa
Author-email: luka.malisha@gmail.com
License: MIT
Keywords: stream,parallel,distributed
Platform: any
Classifier: Development Status :: 3 - Alpha
Classifier: Intended Audience :: Developers
Classifier: License :: OSI Approved :: MIT License
Classifier: Programming Language :: Python :: 2
Classifier: Programming Language :: Python :: 3
